.gitignore
.project
CHANGES.txt
COPYRIGHT.txt
LICENSE.txt
README.txt
buildout.cfg
demo-clients.ini
demo-passwd
demo-who.ini
demo.ini
setup.cfg
setup.py
bin/.keep
src/yasso/__init__.py
src/yasso/authorizeviews.py
src/yasso/main.py
src/yasso/models.py
src/yasso/policy.py
src/yasso/resourceviews.py
src/yasso/tokenviews.py
src/yasso.egg-info/PKG-INFO
src/yasso.egg-info/SOURCES.txt
src/yasso.egg-info/dependency_links.txt
src/yasso.egg-info/entry_points.txt
src/yasso.egg-info/not-zip-safe
src/yasso.egg-info/requires.txt
src/yasso.egg-info/top_level.txt
src/yasso/static/favicon.ico
src/yasso/static/footerbg.png
src/yasso/static/headerbg.png
src/yasso/static/ie6.css
src/yasso/static/middlebg.png
src/yasso/static/pylons.css
src/yasso/static/pyramid-small.png
src/yasso/static/pyramid.png
src/yasso/static/transparent.gif
src/yasso/static/yasso.css
src/yasso/templates/authorize.pt
src/yasso/templates/main.pt
src/yasso/templates/redirect.pt
src/yasso/tests/__init__.py